autocli/__init__.py
autocli/parser.py
autocli_llm-0.2.0.dist-info/licenses/LICENSE
autocli_llm-0.2.0.dist-info/METADATA
autocli_llm-0.2.0.dist-info/WHEEL
autocli_llm-0.2.0.dist-info/top_level.txt
autocli_llm-0.2.0.dist-info/RECORD
