Metadata-Version: 2.4
Name: autocli-llm
Version: 0.2.0
Summary: Parse CLI arguments from natural language using LLMs
Home-page: https://github.com/horatio-sans-serif/autocli
Author: Horatio Sans Serif
Author-email: Horatio Sans Serif <horatio@sans-serif.net>
License: MIT
Project-URL: Homepage, https://github.com/horatio-sans-serif/autocli
Project-URL: Bug Tracker, https://github.com/horatio-sans-serif/autocli/issues
Classifier: Development Status :: 3 - Alpha
Classifier: Intended Audience :: Developers
Classifier: Topic :: Software Development :: Libraries :: Python Modules
Classifier: License :: OSI Approved :: MIT License
Classifier: Programming Language :: Python :: 3
Classifier: Programming Language :: Python :: 3.8
Classifier: Programming Language :: Python :: 3.9
Classifier: Programming Language :: Python :: 3.10
Classifier: Programming Language :: Python :: 3.11
Classifier: Programming Language :: Python :: 3.12
Requires-Python: >=3.8
License-File: LICENSE
Requires-Dist: transformers>=4.30.0
Requires-Dist: torch>=2.0.0
Requires-Dist: sentencepiece>=0.1.99
Requires-Dist: protobuf>=3.20.0
Provides-Extra: dev
Requires-Dist: pytest>=7.0.0; extra == "dev"
Requires-Dist: black>=22.0.0; extra == "dev"
Requires-Dist: flake8>=4.0.0; extra == "dev"
Requires-Dist: mypy>=0.990; extra == "dev"
Dynamic: author
Dynamic: home-page
Dynamic: license-file
Dynamic: requires-python
